{
  "action": "synchronize",
  "after": "0d60e784ffd9a4d779104e17320bc445cac21573",
  "before": "0650b2b49dcb2d853c05549e3c5782396ca1661a",
  "number": 10,
  "pull_request": {
    "_links": {
      "comments": {
        "href": "https://api.github.com/repos/mikedelgaudio/test/issues/10/comments"
      },
      "commits": {
        "href": "https://api.github.com/repos/mikedelgaudio/test/pulls/10/commits"
      },
      "html": { "href": "https://github.com/mikedelgaudio/test/pull/10" },
      "issue": {
        "href": "https://api.github.com/repos/mikedelgaudio/test/issues/10"
      },
      "review_comment": {
        "href": "https://api.github.com/repos/mikedelgaudio/test/pulls/comments{/number}"
      },
      "review_comments": {
        "href": "https://api.github.com/repos/mikedelgaudio/test/pulls/10/comments"
      },
      "self": {
        "href": "https://api.github.com/repos/mikedelgaudio/test/pulls/10"
      },
      "statuses": {
        "href": "https://api.github.com/repos/mikedelgaudio/test/statuses/0d60e784ffd9a4d779104e17320bc445cac21573"
      }
    },
    "active_lock_reason": null,
    "additions": 6,
    "assignee": null,
    "assignees": [],
    "author_association": "NONE",
    "auto_merge": null,
    "base": {
      "label": "mikedelgaudio:main",
      "ref": "main",
      "repo": {
        "allow_auto_merge": false,
        "allow_forking": true,
        "allow_merge_commit": true,
        "allow_rebase_merge": true,
        "allow_squash_merge": true,
        "allow_update_branch": false,
        "archive_url": "https://api.github.com/repos/mikedelgaudio/test/{archive_format}{/ref}",
        "archived": false,
        "assignees_url": "https://api.github.com/repos/mikedelgaudio/test/assignees{/user}",
        "blobs_url": "https://api.github.com/repos/mikedelgaudio/test/git/blobs{/sha}",
        "branches_url": "https://api.github.com/repos/mikedelgaudio/test/branches{/branch}",
        "clone_url": "https://github.com/mikedelgaudio/test.git",
        "collaborators_url": "https://api.github.com/repos/mikedelgaudio/test/collaborators{/collaborator}",
        "comments_url": "https://api.github.com/repos/mikedelgaudio/test/comments{/number}",
        "commits_url": "https://api.github.com/repos/mikedelgaudio/test/commits{/sha}",
        "compare_url": "https://api.github.com/repos/mikedelgaudio/test/compare/{base}...{head}",
        "contents_url": "https://api.github.com/repos/mikedelgaudio/test/contents/{+path}",
        "contributors_url": "https://api.github.com/repos/mikedelgaudio/test/contributors",
        "created_at": "2023-01-20T14:57:21Z",
        "default_branch": "main",
        "delete_branch_on_merge": false,
        "deployments_url": "https://api.github.com/repos/mikedelgaudio/test/deployments",
        "description": null,
        "disabled": false,
        "downloads_url": "https://api.github.com/repos/mikedelgaudio/test/downloads",
        "events_url": "https://api.github.com/repos/mikedelgaudio/test/events",
        "fork": false,
        "forks": 0,
        "forks_count": 0,
        "forks_url": "https://api.github.com/repos/mikedelgaudio/test/forks",
        "full_name": "mikedelgaudio/test",
        "git_commits_url": "https://api.github.com/repos/mikedelgaudio/test/git/commits{/sha}",
        "git_refs_url": "https://api.github.com/repos/mikedelgaudio/test/git/refs{/sha}",
        "git_tags_url": "https://api.github.com/repos/mikedelgaudio/test/git/tags{/sha}",
        "git_url": "git://github.com/mikedelgaudio/test.git",
        "has_discussions": false,
        "has_downloads": true,
        "has_issues": true,
        "has_pages": false,
        "has_projects": true,
        "has_wiki": true,
        "homepage": null,
        "hooks_url": "https://api.github.com/repos/mikedelgaudio/test/hooks",
        "html_url": "https://github.com/mikedelgaudio/test",
        "id": 591354969,
        "is_template": false,
        "issue_comment_url": "https://api.github.com/repos/mikedelgaudio/test/issues/comments{/number}",
        "issue_events_url": "https://api.github.com/repos/mikedelgaudio/test/issues/events{/number}",
        "issues_url": "https://api.github.com/repos/mikedelgaudio/test/issues{/number}",
        "keys_url": "https://api.github.com/repos/mikedelgaudio/test/keys{/key_id}",
        "labels_url": "https://api.github.com/repos/mikedelgaudio/test/labels{/name}",
        "language": "HTML",
        "languages_url": "https://api.github.com/repos/mikedelgaudio/test/languages",
        "license": null,
        "merge_commit_message": "PR_TITLE",
        "merge_commit_title": "MERGE_MESSAGE",
        "merges_url": "https://api.github.com/repos/mikedelgaudio/test/merges",
        "milestones_url": "https://api.github.com/repos/mikedelgaudio/test/milestones{/number}",
        "mirror_url": null,
        "name": "test",
        "node_id": "R_kgDOIz9cWQ",
        "notifications_url": "https://api.github.com/repos/mikedelgaudio/test/notifications{?since,all,participating}",
        "open_issues": 2,
        "open_issues_count": 2,
        "owner": {
          "avatar_url": "https://avatars.githubusercontent.com/u/43451174?v=4",
          "events_url": "https://api.github.com/users/mikedelgaudio/events{/privacy}",
          "followers_url": "https://api.github.com/users/mikedelgaudio/followers",
          "following_url": "https://api.github.com/users/mikedelgaudio/following{/other_user}",
          "gists_url": "https://api.github.com/users/mikedelgaudio/gists{/gist_id}",
          "gravatar_id": "",
          "html_url": "https://github.com/mikedelgaudio",
          "id": 43451174,
          "login": "mikedelgaudio",
          "node_id": "MDQ6VXNlcjQzNDUxMTc0",
          "organizations_url": "https://api.github.com/users/mikedelgaudio/orgs",
          "received_events_url": "https://api.github.com/users/mikedelgaudio/received_events",
          "repos_url": "https://api.github.com/users/mikedelgaudio/repos",
          "site_admin": false,
          "starred_url": "https://api.github.com/users/mikedelgaudio/starred{/owner}{/repo}",
          "subscriptions_url": "https://api.github.com/users/mikedelgaudio/subscriptions",
          "type": "User",
          "url": "https://api.github.com/users/mikedelgaudio"
        },
        "private": false,
        "pulls_url": "https://api.github.com/repos/mikedelgaudio/test/pulls{/number}",
        "pushed_at": "2023-01-25T16:25:52Z",
        "releases_url": "https://api.github.com/repos/mikedelgaudio/test/releases{/id}",
        "size": 457,
        "squash_merge_commit_message": "COMMIT_MESSAGES",
        "squash_merge_commit_title": "COMMIT_OR_PR_TITLE",
        "ssh_url": "git@github.com:mikedelgaudio/test.git",
        "stargazers_count": 0,
        "stargazers_url": "https://api.github.com/repos/mikedelgaudio/test/stargazers",
        "statuses_url": "https://api.github.com/repos/mikedelgaudio/test/statuses/{sha}",
        "subscribers_url": "https://api.github.com/repos/mikedelgaudio/test/subscribers",
        "subscription_url": "https://api.github.com/repos/mikedelgaudio/test/subscription",
        "svn_url": "https://github.com/mikedelgaudio/test",
        "tags_url": "https://api.github.com/repos/mikedelgaudio/test/tags",
        "teams_url": "https://api.github.com/repos/mikedelgaudio/test/teams",
        "topics": [],
        "trees_url": "https://api.github.com/repos/mikedelgaudio/test/git/trees{/sha}",
        "updated_at": "2023-01-20T15:02:00Z",
        "url": "https://api.github.com/repos/mikedelgaudio/test",
        "use_squash_pr_title_as_default": false,
        "visibility": "public",
        "watchers": 0,
        "watchers_count": 0,
        "web_commit_signoff_required": false
      },
      "sha": "788dc3cf40c9ca32f765708ecad38a76ca406ead",
      "user": {
        "avatar_url": "https://avatars.githubusercontent.com/u/43451174?v=4",
        "events_url": "https://api.github.com/users/mikedelgaudio/events{/privacy}",
        "followers_url": "https://api.github.com/users/mikedelgaudio/followers",
        "following_url": "https://api.github.com/users/mikedelgaudio/following{/other_user}",
        "gists_url": "https://api.github.com/users/mikedelgaudio/gists{/gist_id}",
        "gravatar_id": "",
        "html_url": "https://github.com/mikedelgaudio",
        "id": 43451174,
        "login": "mikedelgaudio",
        "node_id": "MDQ6VXNlcjQzNDUxMTc0",
        "organizations_url": "https://api.github.com/users/mikedelgaudio/orgs",
        "received_events_url": "https://api.github.com/users/mikedelgaudio/received_events",
        "repos_url": "https://api.github.com/users/mikedelgaudio/repos",
        "site_admin": false,
        "starred_url": "https://api.github.com/users/mikedelgaudio/starred{/owner}{/repo}",
        "subscriptions_url": "https://api.github.com/users/mikedelgaudio/subscriptions",
        "type": "User",
        "url": "https://api.github.com/users/mikedelgaudio"
      }
    },
    "body": "Bumps [ua-parser-js](https://github.com/faisalman/ua-parser-js) from 0.7.32 to 0.7.33.\n<details>\n<summary>Changelog</summary>\n<p><em>Sourced from <a href=\"https://github.com/faisalman/ua-parser-js/blob/master/changelog.md\">ua-parser-js's changelog</a>.</em></p>\n<blockquote>\n<h2>Version 0.7.32 / 1.0.32</h2>\n<ul>\n<li>Add new browser : DuckDuckGo, Huawei Browser, LinkedIn</li>\n<li>Add new OS : HarmonyOS</li>\n<li>Add some Huawei models</li>\n<li>Add Sharp Aquos TV</li>\n<li>Improve detection Xiaomi Mi CC9</li>\n<li>Fix Sony Xperia 1 III misidentified as Acer tablet</li>\n<li>Fix Detect Sony BRAVIA as SmartTV</li>\n<li>Fix Detect Xiaomi Mi TV as SmartTV</li>\n<li>Fix Detect Galaxy Tab S8 as tablet</li>\n<li>Fix WeGame mistakenly identified as WeChat</li>\n<li>Fix included commas in Safari / Mobile Safari version</li>\n<li>Increase UA_MAX_LENGTH to 350</li>\n</ul>\n<h2>Version 0.7.33 / 1.0.33</h2>\n<ul>\n<li>Add new browser : Cobalt</li>\n<li>Identify Macintosh as an Apple device</li>\n<li>Fix ReDoS vulnerability</li>\n</ul>\n<h1>Version 0.8</h1>\n<p>Version 0.8 was created by accident. This version is now deprecated and no longer maintained, please update to version 0.7 / 1.0.</p>\n</blockquote>\n</details>\n<details>\n<summary>Commits</summary>\n<ul>\n<li><a href=\"https://github.com/faisalman/ua-parser-js/commit/f2d0db001d87da15de7b9b1df7be9f2eacefd8c5\"><code>f2d0db0</code></a> Bump version 0.7.33</li>\n<li><a href=\"https://github.com/faisalman/ua-parser-js/commit/a6140a17dd0300a35cfc9cff999545f267889411\"><code>a6140a1</code></a> Remove unsafe regex in trim() function</li>\n<li><a href=\"https://github.com/faisalman/ua-parser-js/commit/a88660493568d6144a551424a8139d6c876635f6\"><code>a886604</code></a> Fix <a href=\"https://github-redirect.dependabot.com/faisalman/ua-parser-js/issues/605\">#605</a> - Identify Macintosh as Apple device</li>\n<li><a href=\"https://github.com/faisalman/ua-parser-js/commit/b814bcd79198e730936c82462e2d729eb5423e3c\"><code>b814bcd</code></a> Merge pull request <a href=\"https://github-redirect.dependabot.com/faisalman/ua-parser-js/issues/606\">#606</a> from rileyjshaw/patch-1</li>\n<li><a href=\"https://github.com/faisalman/ua-parser-js/commit/7f71024161399b7aa5d5cd10dba9e059f0218262\"><code>7f71024</code></a> Fix documentation</li>\n<li><a href=\"https://github.com/faisalman/ua-parser-js/commit/c239ac5167abd574a635cb809a2b4fa35810d23b\"><code>c239ac5</code></a> Merge pull request <a href=\"https://github-redirect.dependabot.com/faisalman/ua-parser-js/issues/604\">#604</a> from obecerra3/master</li>\n<li><a href=\"https://github.com/faisalman/ua-parser-js/commit/8d3c2d327cf540ff2c050f1cc67bca8c6f8e4458\"><code>8d3c2d3</code></a> Add new browser: Cobalt</li>\n<li>See full diff in <a href=\"https://github.com/faisalman/ua-parser-js/compare/0.7.32...0.7.33\">compare view</a></li>\n</ul>\n</details>\n<br />\n\n\n[![Dependabot compatibility score](https://dependabot-badges.githubapp.com/badges/compatibility_score?dependency-name=ua-parser-js&package-manager=npm_and_yarn&previous-version=0.7.32&new-version=0.7.33)](https://docs.github.com/en/github/managing-security-vulnerabilities/about-dependabot-security-updates#about-compatibility-scores)\n\nDependabot will resolve any conflicts with this PR as long as you don't alter it yourself. You can also trigger a rebase manually by commenting `@dependabot rebase`.\n\n[//]: # (dependabot-automerge-start)\n[//]: # (dependabot-automerge-end)\n\n---\n\n<details>\n<summary>Dependabot commands and options</summary>\n<br />\n\nYou can trigger Dependabot actions by commenting on this PR:\n- `@dependabot rebase` will rebase this PR\n- `@dependabot recreate` will recreate this PR, overwriting any edits that have been made to it\n- `@dependabot merge` will merge this PR after your CI passes on it\n- `@dependabot squash and merge` will squash and merge this PR after your CI passes on it\n- `@dependabot cancel merge` will cancel a previously requested merge and block automerging\n- `@dependabot reopen` will reopen this PR if it is closed\n- `@dependabot close` will close this PR and stop Dependabot recreating it. You can achieve the same result by closing it manually\n- `@dependabot ignore this major version` will close this PR and stop Dependabot creating any more for this major version (unless you reopen the PR or upgrade to it yourself)\n- `@dependabot ignore this minor version` will close this PR and stop Dependabot creating any more for this minor version (unless you reopen the PR or upgrade to it yourself)\n- `@dependabot ignore this dependency` will close this PR and stop Dependabot creating any more for this dependency (unless you reopen the PR or upgrade to it yourself)\n- `@dependabot use these labels` will set the current labels as the default for future PRs for this repo and language\n- `@dependabot use these reviewers` will set the current reviewers as the default for future PRs for this repo and language\n- `@dependabot use these assignees` will set the current assignees as the default for future PRs for this repo and language\n- `@dependabot use this milestone` will set the current milestone as the default for future PRs for this repo and language\n\nYou can disable automated security fix PRs for this repo from the [Security Alerts page](https://github.com/mikedelgaudio/test/network/alerts).\n\n</details>",
    "changed_files": 1,
    "closed_at": null,
    "comments": 0,
    "comments_url": "https://api.github.com/repos/mikedelgaudio/test/issues/10/comments",
    "commits": 4,
    "commits_url": "https://api.github.com/repos/mikedelgaudio/test/pulls/10/commits",
    "created_at": "2023-01-24T17:47:41Z",
    "deletions": 6,
    "diff_url": "https://github.com/mikedelgaudio/test/pull/10.diff",
    "draft": false,
    "head": {
      "label": "mikedelgaudio:dependabot/npm_and_yarn/frontend/ua-parser-js-0.7.33",
      "ref": "dependabot/npm_and_yarn/frontend/ua-parser-js-0.7.33",
      "repo": {
        "allow_auto_merge": false,
        "allow_forking": true,
        "allow_merge_commit": true,
        "allow_rebase_merge": true,
        "allow_squash_merge": true,
        "allow_update_branch": false,
        "archive_url": "https://api.github.com/repos/mikedelgaudio/test/{archive_format}{/ref}",
        "archived": false,
        "assignees_url": "https://api.github.com/repos/mikedelgaudio/test/assignees{/user}",
        "blobs_url": "https://api.github.com/repos/mikedelgaudio/test/git/blobs{/sha}",
        "branches_url": "https://api.github.com/repos/mikedelgaudio/test/branches{/branch}",
        "clone_url": "https://github.com/mikedelgaudio/test.git",
        "collaborators_url": "https://api.github.com/repos/mikedelgaudio/test/collaborators{/collaborator}",
        "comments_url": "https://api.github.com/repos/mikedelgaudio/test/comments{/number}",
        "commits_url": "https://api.github.com/repos/mikedelgaudio/test/commits{/sha}",
        "compare_url": "https://api.github.com/repos/mikedelgaudio/test/compare/{base}...{head}",
        "contents_url": "https://api.github.com/repos/mikedelgaudio/test/contents/{+path}",
        "contributors_url": "https://api.github.com/repos/mikedelgaudio/test/contributors",
        "created_at": "2023-01-20T14:57:21Z",
        "default_branch": "main",
        "delete_branch_on_merge": false,
        "deployments_url": "https://api.github.com/repos/mikedelgaudio/test/deployments",
        "description": null,
        "disabled": false,
        "downloads_url": "https://api.github.com/repos/mikedelgaudio/test/downloads",
        "events_url": "https://api.github.com/repos/mikedelgaudio/test/events",
        "fork": false,
        "forks": 0,
        "forks_count": 0,
        "forks_url": "https://api.github.com/repos/mikedelgaudio/test/forks",
        "full_name": "mikedelgaudio/test",
        "git_commits_url": "https://api.github.com/repos/mikedelgaudio/test/git/commits{/sha}",
        "git_refs_url": "https://api.github.com/repos/mikedelgaudio/test/git/refs{/sha}",
        "git_tags_url": "https://api.github.com/repos/mikedelgaudio/test/git/tags{/sha}",
        "git_url": "git://github.com/mikedelgaudio/test.git",
        "has_discussions": false,
        "has_downloads": true,
        "has_issues": true,
        "has_pages": false,
        "has_projects": true,
        "has_wiki": true,
        "homepage": null,
        "hooks_url": "https://api.github.com/repos/mikedelgaudio/test/hooks",
        "html_url": "https://github.com/mikedelgaudio/test",
        "id": 591354969,
        "is_template": false,
        "issue_comment_url": "https://api.github.com/repos/mikedelgaudio/test/issues/comments{/number}",
        "issue_events_url": "https://api.github.com/repos/mikedelgaudio/test/issues/events{/number}",
        "issues_url": "https://api.github.com/repos/mikedelgaudio/test/issues{/number}",
        "keys_url": "https://api.github.com/repos/mikedelgaudio/test/keys{/key_id}",
        "labels_url": "https://api.github.com/repos/mikedelgaudio/test/labels{/name}",
        "language": "HTML",
        "languages_url": "https://api.github.com/repos/mikedelgaudio/test/languages",
        "license": null,
        "merge_commit_message": "PR_TITLE",
        "merge_commit_title": "MERGE_MESSAGE",
        "merges_url": "https://api.github.com/repos/mikedelgaudio/test/merges",
        "milestones_url": "https://api.github.com/repos/mikedelgaudio/test/milestones{/number}",
        "mirror_url": null,
        "name": "test",
        "node_id": "R_kgDOIz9cWQ",
        "notifications_url": "https://api.github.com/repos/mikedelgaudio/test/notifications{?since,all,participating}",
        "open_issues": 2,
        "open_issues_count": 2,
        "owner": {
          "avatar_url": "https://avatars.githubusercontent.com/u/43451174?v=4",
          "events_url": "https://api.github.com/users/mikedelgaudio/events{/privacy}",
          "followers_url": "https://api.github.com/users/mikedelgaudio/followers",
          "following_url": "https://api.github.com/users/mikedelgaudio/following{/other_user}",
          "gists_url": "https://api.github.com/users/mikedelgaudio/gists{/gist_id}",
          "gravatar_id": "",
          "html_url": "https://github.com/mikedelgaudio",
          "id": 43451174,
          "login": "mikedelgaudio",
          "node_id": "MDQ6VXNlcjQzNDUxMTc0",
          "organizations_url": "https://api.github.com/users/mikedelgaudio/orgs",
          "received_events_url": "https://api.github.com/users/mikedelgaudio/received_events",
          "repos_url": "https://api.github.com/users/mikedelgaudio/repos",
          "site_admin": false,
          "starred_url": "https://api.github.com/users/mikedelgaudio/starred{/owner}{/repo}",
          "subscriptions_url": "https://api.github.com/users/mikedelgaudio/subscriptions",
          "type": "User",
          "url": "https://api.github.com/users/mikedelgaudio"
        },
        "private": false,
        "pulls_url": "https://api.github.com/repos/mikedelgaudio/test/pulls{/number}",
        "pushed_at": "2023-01-25T16:25:52Z",
        "releases_url": "https://api.github.com/repos/mikedelgaudio/test/releases{/id}",
        "size": 457,
        "squash_merge_commit_message": "COMMIT_MESSAGES",
        "squash_merge_commit_title": "COMMIT_OR_PR_TITLE",
        "ssh_url": "git@github.com:mikedelgaudio/test.git",
        "stargazers_count": 0,
        "stargazers_url": "https://api.github.com/repos/mikedelgaudio/test/stargazers",
        "statuses_url": "https://api.github.com/repos/mikedelgaudio/test/statuses/{sha}",
        "subscribers_url": "https://api.github.com/repos/mikedelgaudio/test/subscribers",
        "subscription_url": "https://api.github.com/repos/mikedelgaudio/test/subscription",
        "svn_url": "https://github.com/mikedelgaudio/test",
        "tags_url": "https://api.github.com/repos/mikedelgaudio/test/tags",
        "teams_url": "https://api.github.com/repos/mikedelgaudio/test/teams",
        "topics": [],
        "trees_url": "https://api.github.com/repos/mikedelgaudio/test/git/trees{/sha}",
        "updated_at": "2023-01-20T15:02:00Z",
        "url": "https://api.github.com/repos/mikedelgaudio/test",
        "use_squash_pr_title_as_default": false,
        "visibility": "public",
        "watchers": 0,
        "watchers_count": 0,
        "web_commit_signoff_required": false
      },
      "sha": "0d60e784ffd9a4d779104e17320bc445cac21573",
      "user": {
        "avatar_url": "https://avatars.githubusercontent.com/u/43451174?v=4",
        "events_url": "https://api.github.com/users/mikedelgaudio/events{/privacy}",
        "followers_url": "https://api.github.com/users/mikedelgaudio/followers",
        "following_url": "https://api.github.com/users/mikedelgaudio/following{/other_user}",
        "gists_url": "https://api.github.com/users/mikedelgaudio/gists{/gist_id}",
        "gravatar_id": "",
        "html_url": "https://github.com/mikedelgaudio",
        "id": 43451174,
        "login": "mikedelgaudio",
        "node_id": "MDQ6VXNlcjQzNDUxMTc0",
        "organizations_url": "https://api.github.com/users/mikedelgaudio/orgs",
        "received_events_url": "https://api.github.com/users/mikedelgaudio/received_events",
        "repos_url": "https://api.github.com/users/mikedelgaudio/repos",
        "site_admin": false,
        "starred_url": "https://api.github.com/users/mikedelgaudio/starred{/owner}{/repo}",
        "subscriptions_url": "https://api.github.com/users/mikedelgaudio/subscriptions",
        "type": "User",
        "url": "https://api.github.com/users/mikedelgaudio"
      }
    },
    "html_url": "https://github.com/mikedelgaudio/test/pull/10",
    "id": 1215479153,
    "issue_url": "https://api.github.com/repos/mikedelgaudio/test/issues/10",
    "labels": [
      {
        "color": "0366d6",
        "default": false,
        "description": "Pull requests that update a dependency file",
        "id": 5074473933,
        "name": "dependencies",
        "node_id": "LA_kwDOIz9cWc8AAAABLnZTzQ",
        "url": "https://api.github.com/repos/mikedelgaudio/test/labels/dependencies"
      }
    ],
    "locked": false,
    "maintainer_can_modify": false,
    "merge_commit_sha": "5dd46d24b6188fe6d159ae0852f1fc454ddd6c4a",
    "mergeable": true,
    "mergeable_state": "unstable",
    "merged": false,
    "merged_at": null,
    "merged_by": null,
    "milestone": null,
    "node_id": "PR_kwDOIz9cWc5Icr1x",
    "number": 10,
    "patch_url": "https://github.com/mikedelgaudio/test/pull/10.patch",
    "rebaseable": true,
    "requested_reviewers": [],
    "requested_teams": [],
    "review_comment_url": "https://api.github.com/repos/mikedelgaudio/test/pulls/comments{/number}",
    "review_comments": 0,
    "review_comments_url": "https://api.github.com/repos/mikedelgaudio/test/pulls/10/comments",
    "state": "open",
    "statuses_url": "https://api.github.com/repos/mikedelgaudio/test/statuses/0d60e784ffd9a4d779104e17320bc445cac21573",
    "title": "Bump ua-parser-js from 0.7.32 to 0.7.33 in /frontend",
    "updated_at": "2023-01-25T16:25:52Z",
    "url": "https://api.github.com/repos/mikedelgaudio/test/pulls/10",
    "user": {
      "avatar_url": "https://avatars.githubusercontent.com/in/29110?v=4",
      "events_url": "https://api.github.com/users/dependabot%5Bbot%5D/events{/privacy}",
      "followers_url": "https://api.github.com/users/dependabot%5Bbot%5D/followers",
      "following_url": "https://api.github.com/users/dependabot%5Bbot%5D/following{/other_user}",
      "gists_url": "https://api.github.com/users/dependabot%5Bbot%5D/gists{/gist_id}",
      "gravatar_id": "",
      "html_url": "https://github.com/apps/dependabot",
      "id": 49699333,
      "login": "dependabot[bot]",
      "node_id": "MDM6Qm90NDk2OTkzMzM=",
      "organizations_url": "https://api.github.com/users/dependabot%5Bbot%5D/orgs",
      "received_events_url": "https://api.github.com/users/dependabot%5Bbot%5D/received_events",
      "repos_url": "https://api.github.com/users/dependabot%5Bbot%5D/repos",
      "site_admin": false,
      "starred_url": "https://api.github.com/users/dependabot%5Bbot%5D/starred{/owner}{/repo}",
      "subscriptions_url": "https://api.github.com/users/dependabot%5Bbot%5D/subscriptions",
      "type": "Bot",
      "url": "https://api.github.com/users/dependabot%5Bbot%5D"
    }
  },
  "repository": {
    "allow_forking": true,
    "archive_url": "https://api.github.com/repos/mikedelgaudio/test/{archive_format}{/ref}",
    "archived": false,
    "assignees_url": "https://api.github.com/repos/mikedelgaudio/test/assignees{/user}",
    "blobs_url": "https://api.github.com/repos/mikedelgaudio/test/git/blobs{/sha}",
    "branches_url": "https://api.github.com/repos/mikedelgaudio/test/branches{/branch}",
    "clone_url": "https://github.com/mikedelgaudio/test.git",
    "collaborators_url": "https://api.github.com/repos/mikedelgaudio/test/collaborators{/collaborator}",
    "comments_url": "https://api.github.com/repos/mikedelgaudio/test/comments{/number}",
    "commits_url": "https://api.github.com/repos/mikedelgaudio/test/commits{/sha}",
    "compare_url": "https://api.github.com/repos/mikedelgaudio/test/compare/{base}...{head}",
    "contents_url": "https://api.github.com/repos/mikedelgaudio/test/contents/{+path}",
    "contributors_url": "https://api.github.com/repos/mikedelgaudio/test/contributors",
    "created_at": "2023-01-20T14:57:21Z",
    "default_branch": "main",
    "deployments_url": "https://api.github.com/repos/mikedelgaudio/test/deployments",
    "description": null,
    "disabled": false,
    "downloads_url": "https://api.github.com/repos/mikedelgaudio/test/downloads",
    "events_url": "https://api.github.com/repos/mikedelgaudio/test/events",
    "fork": false,
    "forks": 0,
    "forks_count": 0,
    "forks_url": "https://api.github.com/repos/mikedelgaudio/test/forks",
    "full_name": "mikedelgaudio/test",
    "git_commits_url": "https://api.github.com/repos/mikedelgaudio/test/git/commits{/sha}",
    "git_refs_url": "https://api.github.com/repos/mikedelgaudio/test/git/refs{/sha}",
    "git_tags_url": "https://api.github.com/repos/mikedelgaudio/test/git/tags{/sha}",
    "git_url": "git://github.com/mikedelgaudio/test.git",
    "has_discussions": false,
    "has_downloads": true,
    "has_issues": true,
    "has_pages": false,
    "has_projects": true,
    "has_wiki": true,
    "homepage": null,
    "hooks_url": "https://api.github.com/repos/mikedelgaudio/test/hooks",
    "html_url": "https://github.com/mikedelgaudio/test",
    "id": 591354969,
    "is_template": false,
    "issue_comment_url": "https://api.github.com/repos/mikedelgaudio/test/issues/comments{/number}",
    "issue_events_url": "https://api.github.com/repos/mikedelgaudio/test/issues/events{/number}",
    "issues_url": "https://api.github.com/repos/mikedelgaudio/test/issues{/number}",
    "keys_url": "https://api.github.com/repos/mikedelgaudio/test/keys{/key_id}",
    "labels_url": "https://api.github.com/repos/mikedelgaudio/test/labels{/name}",
    "language": "HTML",
    "languages_url": "https://api.github.com/repos/mikedelgaudio/test/languages",
    "license": null,
    "merges_url": "https://api.github.com/repos/mikedelgaudio/test/merges",
    "milestones_url": "https://api.github.com/repos/mikedelgaudio/test/milestones{/number}",
    "mirror_url": null,
    "name": "test",
    "node_id": "R_kgDOIz9cWQ",
    "notifications_url": "https://api.github.com/repos/mikedelgaudio/test/notifications{?since,all,participating}",
    "open_issues": 2,
    "open_issues_count": 2,
    "owner": {
      "avatar_url": "https://avatars.githubusercontent.com/u/43451174?v=4",
      "events_url": "https://api.github.com/users/mikedelgaudio/events{/privacy}",
      "followers_url": "https://api.github.com/users/mikedelgaudio/followers",
      "following_url": "https://api.github.com/users/mikedelgaudio/following{/other_user}",
      "gists_url": "https://api.github.com/users/mikedelgaudio/gists{/gist_id}",
      "gravatar_id": "",
      "html_url": "https://github.com/mikedelgaudio",
      "id": 43451174,
      "login": "mikedelgaudio",
      "node_id": "MDQ6VXNlcjQzNDUxMTc0",
      "organizations_url": "https://api.github.com/users/mikedelgaudio/orgs",
      "received_events_url": "https://api.github.com/users/mikedelgaudio/received_events",
      "repos_url": "https://api.github.com/users/mikedelgaudio/repos",
      "site_admin": false,
      "starred_url": "https://api.github.com/users/mikedelgaudio/starred{/owner}{/repo}",
      "subscriptions_url": "https://api.github.com/users/mikedelgaudio/subscriptions",
      "type": "User",
      "url": "https://api.github.com/users/mikedelgaudio"
    },
    "private": false,
    "pulls_url": "https://api.github.com/repos/mikedelgaudio/test/pulls{/number}",
    "pushed_at": "2023-01-25T16:25:52Z",
    "releases_url": "https://api.github.com/repos/mikedelgaudio/test/releases{/id}",
    "size": 457,
    "ssh_url": "git@github.com:mikedelgaudio/test.git",
    "stargazers_count": 0,
    "stargazers_url": "https://api.github.com/repos/mikedelgaudio/test/stargazers",
    "statuses_url": "https://api.github.com/repos/mikedelgaudio/test/statuses/{sha}",
    "subscribers_url": "https://api.github.com/repos/mikedelgaudio/test/subscribers",
    "subscription_url": "https://api.github.com/repos/mikedelgaudio/test/subscription",
    "svn_url": "https://github.com/mikedelgaudio/test",
    "tags_url": "https://api.github.com/repos/mikedelgaudio/test/tags",
    "teams_url": "https://api.github.com/repos/mikedelgaudio/test/teams",
    "topics": [],
    "trees_url": "https://api.github.com/repos/mikedelgaudio/test/git/trees{/sha}",
    "updated_at": "2023-01-20T15:02:00Z",
    "url": "https://api.github.com/repos/mikedelgaudio/test",
    "visibility": "public",
    "watchers": 0,
    "watchers_count": 0,
    "web_commit_signoff_required": false
  }
}
